opentelemetry/instrumentation/aliyun_ons_http/__init__.py
opentelemetry/instrumentation/aliyun_ons_http/package.py
opentelemetry/instrumentation/aliyun_ons_http/version.py
opentelemetry_instrumentation_aliyun_ons_http-0.47b1.dist-info/LICENSE
opentelemetry_instrumentation_aliyun_ons_http-0.47b1.dist-info/METADATA
opentelemetry_instrumentation_aliyun_ons_http-0.47b1.dist-info/WHEEL
opentelemetry_instrumentation_aliyun_ons_http-0.47b1.dist-info/entry_points.txt
opentelemetry_instrumentation_aliyun_ons_http-0.47b1.dist-info/top_level.txt
opentelemetry_instrumentation_aliyun_ons_http-0.47b1.dist-info/RECORD
