Metadata-Version: 2.1
Name: opentelemetry-instrumentation-aliyun-ons-http
Version: 0.47b1
Summary: Aliyun ons http api instrumentation for OpenTelemetry
Author-email: fcfangcc <swjfc22@live.com>
Classifier: Development Status :: 4 - Beta
Classifier: Intended Audience :: Developers
Classifier: Programming Language :: Python
Classifier: Programming Language :: Python :: 3.10
Classifier: Programming Language :: Python :: 3.11
Classifier: Programming Language :: Python :: 3.12
Requires-Python: >=3.10
License-File: LICENSE
Requires-Dist: opentelemetry-api ~=1.12
Requires-Dist: opentelemetry-instrumentation ==0.47b0
Requires-Dist: opentelemetry-semantic-conventions ==0.47b0
Requires-Dist: wrapt <2.0.0,>=1.0.0
Provides-Extra: dev
Requires-Dist: build ; extra == 'dev'
Provides-Extra: instruments
Requires-Dist: mq-http-sdk <2.0.0,>1.0.0 ; extra == 'instruments'
